encypher/__init__.py
encypher/config/__init__.py
encypher/config/settings.py
encypher/core/__init__.py
encypher/core/constants.py
encypher/core/crypto_utils.py
encypher/core/exceptions.py
encypher/core/keys.py
encypher/core/logging_config.py
encypher/core/payloads.py
encypher/core/signing.py
encypher/core/unicode_metadata.py
encypher/examples/__init__.py
encypher/examples/c2pa_text_embedding_demo.py
encypher/examples/cli_example.py
encypher/examples/fastapi_example.py
encypher/examples/generate_keys.py
encypher/examples/litellm_integration.py
encypher/examples/youtube_demo.py
encypher/interop/__init__.py
encypher/interop/c2pa_core.py
encypher/interop/c2pa_legacy_module.py
encypher/interop/c2pa/__init__.py
encypher/interop/c2pa/text_hashing.py
encypher/interop/c2pa/text_wrapper.py
encypher/streaming/__init__.py
encypher/streaming/handlers.py
encypher/utils/__init__.py
encypher_ai-3.0.4.dist-info/licenses/LICENSE.md
encypher_ai-3.0.4.dist-info/METADATA
encypher_ai-3.0.4.dist-info/WHEEL
encypher_ai-3.0.4.dist-info/top_level.txt
encypher_ai-3.0.4.dist-info/RECORD
