Metadata-Version: 2.4
Name: encypher-ai
Version: 3.0.4
Summary: Embed invisible metadata in AI-generated text using zero-width characters.
Author: Encypher Team
License-Expression: AGPL-3.0
Project-URL: Homepage, https://github.com/encypherai/encypher-ai
Project-URL: Bug Tracker, https://github.com/encypherai/encypher-ai/issues
Classifier: Programming Language :: Python :: 3
Classifier: Programming Language :: Python :: 3.9
Classifier: Programming Language :: Python :: 3.10
Classifier: Programming Language :: Python :: 3.11
Classifier: Operating System :: OS Independent
Requires-Python: >=3.9
License-File: LICENSE.md
Requires-Dist: rich
Requires-Dist: cryptography
Requires-Dist: cbor2>=5.6.5
Requires-Dist: c2pa-text>=1.0.0
Requires-Dist: requests
Provides-Extra: dev
Requires-Dist: pytest>=7.0.0; extra == "dev"
Requires-Dist: pytest-cov>=4.0.0; extra == "dev"
Requires-Dist: mypy>=1.0.0; extra == "dev"
Requires-Dist: types-requests>=2.31.0; extra == "dev"
Requires-Dist: ruff>=0.0.270; extra == "dev"
Requires-Dist: pre-commit>=3.3.3; extra == "dev"
Requires-Dist: types-Deprecated>=1.2.9; extra == "dev"
Requires-Dist: litellm>=1.43.0; extra == "dev"
Requires-Dist: fastapi; extra == "dev"
Requires-Dist: uvicorn; extra == "dev"
Dynamic: license-file
